elogger/__init__.py
elogger_amadeus-0.0.1.dist-info/LICENSE
elogger_amadeus-0.0.1.dist-info/METADATA
elogger_amadeus-0.0.1.dist-info/WHEEL
elogger_amadeus-0.0.1.dist-info/top_level.txt
elogger_amadeus-0.0.1.dist-info/RECORD
