Metadata-Version: 2.1
Name: elogger-amadeus
Version: 0.0.1
Summary: An easy logger
Home-page: https://github.com/Amadeus9029/elogger
Author: Amadeus9029
Author-email: 965720890@qq.com
License: UNKNOWN
Platform: UNKNOWN
Classifier: Programming Language :: Python :: 3
Classifier: License :: OSI Approved :: MIT License
Classifier: Operating System :: OS Independent
